pyconfigparser.py
python_config_parser-3.1.6.dist-info/licenses/LICENSE-MIT
python_config_parser-3.1.6.dist-info/METADATA
python_config_parser-3.1.6.dist-info/WHEEL
python_config_parser-3.1.6.dist-info/top_level.txt
python_config_parser-3.1.6.dist-info/RECORD
