Metadata-Version: 2.4
Name: python-config-parser
Version: 3.1.6
Summary: Project created to given the possibility of create dynamics config files
Home-page: https://github.com/BrunoSilvaAndrade/python-config-parser
Author: Bruno Silva de Andrade
Author-email: brunojf.andrade@gmail.com
License: MIT
Classifier: Programming Language :: Python :: 3
Classifier: License :: OSI Approved :: MIT License
Classifier: Operating System :: OS Independent
License-File: LICENSE-MIT
Requires-Dist: schema>=0.7.1
Requires-Dist: PyYaml>=3.12.0
Dynamic: author
Dynamic: author-email
Dynamic: classifier
Dynamic: description
Dynamic: description-content-type
Dynamic: home-page
Dynamic: license
Dynamic: license-file
Dynamic: requires-dist
Dynamic: summary
